mynpshuffle/__init__.py
mynpshuffle/shuffle.py
mynpshuffle-0.1.0.dist-info/METADATA
mynpshuffle-0.1.0.dist-info/WHEEL
mynpshuffle-0.1.0.dist-info/top_level.txt
mynpshuffle-0.1.0.dist-info/RECORD
