Metadata-Version: 2.1
Name: mynpshuffle
Version: 0.1.0
Summary: A simple Python package for shuffling an array
Home-page: UNKNOWN
License: UNKNOWN
Platform: UNKNOWN
Classifier: Programming Language :: Python :: 3
Classifier: License :: OSI Approved :: MIT License
Classifier: Operating System :: OS Independent
Requires-Python: >=3.6
